rolldice_binding/__init__.py
rolldice_binding/__main__.py
rolldice_binding/core.py
rolldice_binding/render/__init__.py
rolldice_binding/render/json.py
rolldice_binding/render/pretty.py
rolldice_binding-0.1.dist-info/DESCRIPTION.rst
rolldice_binding-0.1.dist-info/METADATA
rolldice_binding-0.1.dist-info/RECORD
rolldice_binding-0.1.dist-info/WHEEL
rolldice_binding-0.1.dist-info/entry_points.txt
rolldice_binding-0.1.dist-info/metadata.json
rolldice_binding-0.1.dist-info/top_level.txt
