Metadata-Version: 2.0
Name: rolldice-binding
Version: 0.1
Summary: Command line bindings for the py-rolldice library
Home-page: https://github.com/bsmaldon/rolldice-binding
Author: Berin Smaldon
Author-email: noodels555@gmail.com
License: UNKNOWN
Platform: UNKNOWN
Classifier: Programming Language :: Python :: 3.5
Classifier: License :: OSI Approved :: GNU General Public License v3 (GPLv3)
Classifier: Operating System :: OS Independent
Requires-Python: >=3.5
Requires-Dist: py-rolldice
